drypy_airflow/__init__.py
drypy_airflow-0.0.4.dist-info/METADATA
drypy_airflow-0.0.4.dist-info/RECORD
drypy_airflow-0.0.4.dist-info/WHEEL
drypy_airflow-0.0.4.dist-info/top_level.txt
