Metadata-Version: 2.1
Name: drypy-airflow
Version: 0.0.4
Summary: Airflow extensions
Home-page: https://github.com/dhan16/drypy-airflow
Author: dhan16
Author-email: chandan.nath@gmail.com
License: Apache License Version 2.0, January 2004
Platform: UNKNOWN
